sczr_tcp/__init__.py
sczr_tcp/__main__.py
sczr_tcp/cli.py
sczr_tcp-0.1.4.dist-info/entry_points.txt
sczr_tcp-0.1.4.dist-info/WHEEL
sczr_tcp-0.1.4.dist-info/METADATA
sczr_tcp-0.1.4.dist-info/RECORD
