Metadata-Version: 2.1
Name: sczr-tcp
Version: 0.1.4
Summary: 
Author: Michał Rokita
Author-email: mrokita@mrokita.pl
Requires-Python: >=3.9,<4.0
Classifier: Programming Language :: Python :: 3
Classifier: Programming Language :: Python :: 3.9
Requires-Dist: loguru (>=0.5.3,<0.6.0)
Requires-Dist: orjson (>=3.4.6,<4.0.0)
Requires-Dist: pydantic (>=1.7.3,<2.0.0)
Requires-Dist: pygame (>=2.0.0,<3.0.0)
Requires-Dist: typer (>=0.3.2,<0.4.0)
